llama_index/llms/azure_inference/__init__.py
llama_index/llms/azure_inference/base.py
llama_index_llms_azure_inference-0.5.1.dist-info/METADATA
llama_index_llms_azure_inference-0.5.1.dist-info/WHEEL
llama_index_llms_azure_inference-0.5.1.dist-info/licenses/LICENSE
llama_index_llms_azure_inference-0.5.1.dist-info/RECORD
