Metadata-Version: 2.4
Name: llama-index-llms-azure-inference
Version: 0.5.1
Summary: Integration for model supporting Azure AI model inference API in llama-index
Author-email: Azure AI model inference group <azureml-inference@microsoft.com>
License-Expression: MIT
License-File: LICENSE
Requires-Python: <4.0,>=3.9
Requires-Dist: aiohttp<4,>=3.10.0
Requires-Dist: azure-ai-inference>=1.0.0b5
Requires-Dist: azure-identity<2,>=1.15.0
Requires-Dist: llama-index-core<0.15,>=0.13.0
